dbrownell_Email/EmailTee.py
dbrownell_Email/SmtpMailer.py
dbrownell_Email/__init__.py
dbrownell_Email/py.typed
dbrownell_email-0.2.5.dist-info/WHEEL
dbrownell_email-0.2.5.dist-info/entry_points.txt
dbrownell_email-0.2.5.dist-info/METADATA
dbrownell_email-0.2.5.dist-info/RECORD
