Metadata-Version: 2.3
Name: dbrownell-email
Version: 0.2.5
Summary: Email tools and utilities.
Author: David Brownell
Author-email: David Brownell <github@DavidBrownell.com>
License: MIT
Classifier: Operating System :: MacOS
Classifier: Operating System :: Microsoft :: Windows
Classifier: Operating System :: POSIX :: Linux
Classifier: Programming Language :: Python
Classifier: Programming Language :: Python :: 3.13
Classifier: Programming Language :: Python :: 3.12
Classifier: Programming Language :: Python :: 3.11
Classifier: Programming Language :: Python :: 3.10
Requires-Dist: ansi2html>=1.9.2
Requires-Dist: dbrownell-common>=0.16.0
Requires-Dist: pywin32>=310 ; sys_platform == 'win32'
Requires-Dist: typer>=0.15.3
Requires-Python: >=3.10
Project-URL: Documentation, https://github.com/davidbrownell/dbrownell_Email
Project-URL: Homepage, https://github.com/davidbrownell/dbrownell_Email
Project-URL: Repository, https://github.com/davidbrownell/dbrownell_Email
